{"type": "Feature", "id": 12510891, "geometry": {"type": "Point", "coordinates": [89.164398, 23.1833]}, "properties": {"woe:id": 12510891, "woe:parent_id": 1895360, "woe:name": "Jessore Airport", "woe:placetype": 14, "woe:placetype_name": "Airport", "woe:lang": "ENG", "iso:country": "BD", "meta:provider": ["geoplanet:7.3.1", "geoplanet:7.3.2", "geoplanet:7.4.0", "geoplanet:7.4.1", "geoplanet:7.5.1", "geoplanet:7.5.2", "geoplanet:7.6.0", "geoplanet:7.8.1", "geoplanet:7.9.0", "geoplanet:7.10.0", "geoplanet:8.0.0", "woeplanet:8.0.0"], "meta:indexed": "2020-08-20T21:03:11.495230", "woe:alias_ENG_V": ["JSR Airport", "JSR"], "meta:updated": "2020-10-14T12:07:05.916858", "woe:hierarchy": {"continent": 24865671, "country": 23424759, "town": 0, "planet": 1, "county": 23706417, "suburb": 0, "state": 2344792, "region": 0, "localadmin": 0}, "woe:timezone_id": 28350822, "woe:hash": "tup7uurs903g", "woe:centroid": [89.164398, 23.1833], "geom:latitude": 23.1833, "geom:longitude": 89.164398, "geom:hash": "tup7uurs903g", "woe:latitude": 23.1833, "geom:centroid": [89.164398, 23.1833], "woe:longitude": 89.164398, "woe:repo": "woeplanet-airport-bd", "geom:area": 0.0, "woe:scale": 19}}