{"type": "Feature", "id": 12510890, "geometry": {"type": "Point", "coordinates": [89.052803, 24.1528]}, "properties": {"woe:id": 12510890, "woe:parent_id": 1915086, "woe:name": "Ishurdi Airport", "woe:placetype": 14, "woe:placetype_name": "Airport", "woe:lang": "ENG", "iso:country": "BD", "meta:provider": ["geoplanet:7.3.1", "geoplanet:7.3.2", "geoplanet:7.4.0", "geoplanet:7.4.1", "geoplanet:7.5.1", "geoplanet:7.5.2", "geoplanet:7.6.0", "geoplanet:7.8.1", "geoplanet:7.9.0", "geoplanet:7.10.0", "geoplanet:8.0.0", "woeplanet:8.0.0"], "meta:indexed": "2020-08-20T21:03:11.494442", "meta:updated": "2020-10-14T12:07:05.918403", "woe:hierarchy": {"continent": 24865671, "country": 23424759, "town": 0, "planet": 1, "county": 23706444, "suburb": 0, "state": 2344793, "region": 0, "localadmin": 0}, "woe:timezone_id": 28350822, "woe:hash": "tur36kyk28q8", "woe:centroid": [89.052803, 24.1528], "geom:latitude": 24.1528, "geom:longitude": 89.052803, "geom:hash": "tur36kyk28q8", "woe:latitude": 24.1528, "geom:centroid": [89.052803, 24.1528], "woe:longitude": 89.052803, "woe:repo": "woeplanet-airport-bd", "geom:area": 0.0, "woe:scale": 19}}